simple_math/__init__.py
simple_math/calculator.py
simple_math_sdk-0.1.dist-info/METADATA
simple_math_sdk-0.1.dist-info/WHEEL
simple_math_sdk-0.1.dist-info/top_level.txt
simple_math_sdk-0.1.dist-info/RECORD
